{
"0":{"acu_rewards_discounted":40.0,"acu_rewards_undiscounted":40.0,"arrived_mec_state_(s')":1,"arrived_mp_state_(s')":0,"arrived_mr_state_(s')":1,"current_belief_mec_true_(s)":0.5,"current_belief_mp_true_(s)":0.5,"current_belief_mr_true_(s)":0.5,"current_mec_state(s)":0,"current_mp_state(s)":0,"current_mr_state(s)":1,"current_rewards":[[39.0,40.0,38.0,16.0,43.0,28.0,13.0,1.0],[43.0,31.0,28.0,26.0,28.0,16.0,23.0,11.0]],"ev.mst":459.732231928996,"ev.rt":423.176285621515,"flagUpdatedRewards":0,"observation_code":7,"observation_description":"sMEC_x_AND_sMR_s_AND_sMP_f_g","observation_probability":0.14352,"selected_action":"MST","step_reward":40.0,"updated_belief_mec_true_(s')":0.886285101987719,"updated_belief_mp_true_(s')":0.802852675541412,"updated_belief_mr_true_(s')":0.940395424008812},
"1":{"acu_rewards_discounted":78.0,"acu_rewards_undiscounted":80.0,"arrived_mec_state_(s')":1,"arrived_mp_state_(s')":0,"arrived_mr_state_(s')":1,"current_belief_mec_true_(s)":0.886285101987719,"current_belief_mp_true_(s)":0.802852675541412,"current_belief_mr_true_(s)":0.940395424008812,"current_mec_state(s)":1,"current_mp_state(s)":1,"current_mr_state(s)":1,"current_rewards":[[39.0,40.0,38.0,16.0,43.0,28.0,13.0,1.0],[43.0,31.0,28.0,26.0,28.0,16.0,23.0,11.0]],"ev.mst":465.883124793062,"ev.rt":443.092292068951,"flagUpdatedRewards":0,"observation_code":6,"observation_description":"sMEC_x_AND_sMR_s_AND_sMP_f","observation_probability":0.41808,"selected_action":"MST","step_reward":40.0,"updated_belief_mec_true_(s')":0.903391571966742,"updated_belief_mp_true_(s')":0.913822035480314,"updated_belief_mr_true_(s')":0.935699897454853},
"2":{"acu_rewards_discounted":116.8075,"acu_rewards_undiscounted":123.0,"arrived_mec_state_(s')":0,"arrived_mp_state_(s')":1,"arrived_mr_state_(s')":1,"current_belief_mec_true_(s)":0.903391571966742,"current_belief_mp_true_(s)":0.913822035480314,"current_belief_mr_true_(s)":0.935699897454853,"current_mec_state(s)":1,"current_mp_state(s)":1,"current_mr_state(s)":1,"current_rewards":[[39.0,40.0,38.0,16.0,43.0,28.0,13.0,1.0],[43.0,31.0,28.0,26.0,28.0,16.0,23.0,11.0]],"ev.mst":465.173111805632,"ev.rt":449.274027012431,"flagUpdatedRewards":0,"observation_code":6,"observation_description":"sMEC_x_AND_sMR_s_AND_sMP_f","observation_probability":0.466128,"selected_action":"MST","step_reward":43.0,"updated_belief_mec_true_(s')":0.903888447065188,"updated_belief_mp_true_(s')":0.913870948073094,"updated_belief_mr_true_(s')":0.936236749129385},
"3":{"acu_rewards_discounted":140.814,"acu_rewards_undiscounted":151.0,"arrived_mec_state_(s')":0,"arrived_mp_state_(s')":0,"arrived_mr_state_(s')":1,"current_belief_mec_true_(s)":0.903888447065188,"current_belief_mp_true_(s)":0.913870948073094,"current_belief_mr_true_(s)":0.936236749129385,"current_mec_state(s)":1,"current_mp_state(s)":1,"current_mr_state(s)":1,"current_rewards":[[39.0,40.0,38.0,16.0,43.0,28.0,13.0,1.0],[43.0,31.0,28.0,26.0,28.0,16.0,23.0,11.0]],"ev.mst":460.058627705992,"ev.rt":451.787411394484,"flagUpdatedRewards":0,"observation_code":8,"observation_description":"sMEC_x_AND_sMR_s_AND_sMP_g","observation_probability":0.05616,"selected_action":"MST","step_reward":28.0,"updated_belief_mec_true_(s')":0.902402133803591,"updated_belief_mp_true_(s')":0.780923314485029,"updated_belief_mr_true_(s')":0.935435500776315},
"4":{"acu_rewards_discounted":172.57974375,"acu_rewards_undiscounted":190.0,"arrived_mec_state_(s')":1,"arrived_mp_state_(s')":1,"arrived_mr_state_(s')":1,"current_belief_mec_true_(s)":0.902402133803591,"current_belief_mp_true_(s)":0.780923314485029,"current_belief_mr_true_(s)":0.935435500776315,"current_mec_state(s)":1,"current_mp_state(s)":1,"current_mr_state(s)":1,"current_rewards":[[39.0,40.0,38.0,16.0,43.0,28.0,13.0,1.0],[43.0,31.0,28.0,26.0,28.0,16.0,23.0,11.0]],"ev.mst":472.126825654999,"ev.rt":452.144221233745,"flagUpdatedRewards":0,"observation_code":6,"observation_description":"sMEC_x_AND_sMR_s_AND_sMP_f","observation_probability":0.51792,"selected_action":"MST","step_reward":39.0,"updated_belief_mec_true_(s')":0.906694366135072,"updated_belief_mp_true_(s')":0.908509711983581,"updated_belief_mr_true_(s')":0.935161521106257},
"5":{"acu_rewards_discounted":202.7572003125,"acu_rewards_undiscounted":229.0,"arrived_mec_state_(s')":1,"arrived_mp_state_(s')":1,"arrived_mr_state_(s')":1,"current_belief_mec_true_(s)":0.906694366135072,"current_belief_mp_true_(s)":0.908509711983581,"current_belief_mr_true_(s)":0.935161521106257,"current_mec_state(s)":1,"current_mp_state(s)":1,"current_mr_state(s)":1,"current_rewards":[[39.0,40.0,38.0,16.0,43.0,28.0,13.0,1.0],[43.0,31.0,28.0,26.0,28.0,16.0,23.0,11.0]],"ev.mst":456.560907367303,"ev.rt":455.87006987049,"flagUpdatedRewards":0,"observation_code":6,"observation_description":"sMEC_x_AND_sMR_s_AND_sMP_f","observation_probability":0.51792,"selected_action":"MST","step_reward":39.0,"updated_belief_mec_true_(s')":0.90848963854766,"updated_belief_mp_true_(s')":0.913212682515483,"updated_belief_mr_true_(s')":0.93771367693656},
"6":{"acu_rewards_discounted":232.1608759375,"acu_rewards_undiscounted":269.0,"arrived_mec_state_(s')":1,"arrived_mp_state_(s')":0,"arrived_mr_state_(s')":1,"current_belief_mec_true_(s)":0.90848963854766,"current_belief_mp_true_(s)":0.913212682515483,"current_belief_mr_true_(s)":0.93771367693656,"current_mec_state(s)":1,"current_mp_state(s)":1,"current_mr_state(s)":1,"current_rewards":[[39.0,40.0,38.0,16.0,43.0,28.0,13.0,1.0],[43.0,31.0,28.0,26.0,28.0,16.0,23.0,11.0]],"ev.mst":456.736673344943,"ev.rt":440.474158030291,"flagUpdatedRewards":0,"observation_code":7,"observation_description":"sMEC_x_AND_sMR_s_AND_sMP_f_g","observation_probability":0.14352,"selected_action":"MST","step_reward":40.0,"updated_belief_mec_true_(s')":0.903661639054707,"updated_belief_mp_true_(s')":0.825306489504395,"updated_belief_mr_true_(s')":0.93234116342496},
"7":{"acu_rewards_discounted":260.09436778125,"acu_rewards_undiscounted":309.0,"arrived_mec_state_(s')":1,"arrived_mp_state_(s')":0,"arrived_mr_state_(s')":1,"current_belief_mec_true_(s)":0.903661639054707,"current_belief_mp_true_(s)":0.825306489504395,"current_belief_mr_true_(s)":0.93234116342496,"current_mec_state(s)":1,"current_mp_state(s)":1,"current_mr_state(s)":0,"current_rewards":[[39.0,40.0,38.0,16.0,43.0,28.0,13.0,1.0],[43.0,31.0,28.0,26.0,28.0,16.0,23.0,11.0]],"ev.mst":461.608579376743,"ev.rt":442.767560766182,"flagUpdatedRewards":0,"observation_code":6,"observation_description":"sMEC_x_AND_sMR_s_AND_sMP_f","observation_probability":0.41808,"selected_action":"MST","step_reward":40.0,"updated_belief_mec_true_(s')":0.904915683704556,"updated_belief_mp_true_(s')":0.914891482635278,"updated_belief_mr_true_(s')":0.936612677437245},
"8":{"acu_rewards_discounted":285.967764601523,"acu_rewards_undiscounted":348.0,"arrived_mec_state_(s')":1,"arrived_mp_state_(s')":1,"arrived_mr_state_(s')":1,"current_belief_mec_true_(s)":0.904915683704556,"current_belief_mp_true_(s)":0.914891482635278,"current_belief_mr_true_(s)":0.936612677437245,"current_mec_state(s)":1,"current_mp_state(s)":1,"current_mr_state(s)":0,"current_rewards":[[39.0,40.0,38.0,16.0,43.0,28.0,13.0,1.0],[43.0,31.0,28.0,26.0,28.0,16.0,23.0,11.0]],"ev.mst":470.176756820229,"ev.rt":444.33444336615,"flagUpdatedRewards":0,"observation_code":6,"observation_description":"sMEC_x_AND_sMR_s_AND_sMP_f","observation_probability":0.51792,"selected_action":"MST","step_reward":39.0,"updated_belief_mec_true_(s')":0.90621878585826,"updated_belief_mp_true_(s')":0.912516252596732,"updated_belief_mr_true_(s')":0.938545158347765},
"9":{"acu_rewards_discounted":310.547491580783,"acu_rewards_undiscounted":387.0,"arrived_mec_state_(s')":1,"arrived_mp_state_(s')":1,"arrived_mr_state_(s')":1,"current_belief_mec_true_(s)":0.90621878585826,"current_belief_mp_true_(s)":0.912516252596732,"current_belief_mr_true_(s)":0.938545158347765,"current_mec_state(s)":1,"current_mp_state(s)":1,"current_mr_state(s)":1,"current_rewards":[[39.0,40.0,38.0,16.0,43.0,28.0,13.0,1.0],[43.0,31.0,28.0,26.0,28.0,16.0,23.0,11.0]],"ev.mst":456.036396663889,"ev.rt":448.623973114784,"flagUpdatedRewards":0,"observation_code":3,"observation_description":"sMEC_x_AND_sMR_r_s_AND_sMP_f","observation_probability":0.10624,"selected_action":"MST","step_reward":39.0,"updated_belief_mec_true_(s')":0.905534087064961,"updated_belief_mp_true_(s')":0.914147117888247,"updated_belief_mr_true_(s')":0.839613355506341},
"10":{"acu_rewards_discounted":333.299495271842,"acu_rewards_undiscounted":425.0,"arrived_mec_state_(s')":1,"arrived_mp_state_(s')":1,"arrived_mr_state_(s')":0,"current_belief_mec_true_(s)":0.905534087064961,"current_belief_mp_true_(s)":0.914147117888247,"current_belief_mr_true_(s)":0.839613355506341,"current_mec_state(s)":0,"current_mp_state(s)":1,"current_mr_state(s)":1,"current_rewards":[[39.0,40.0,38.0,16.0,43.0,28.0,13.0,1.0],[43.0,31.0,28.0,26.0,28.0,16.0,23.0,11.0]],"ev.mst":462.786008700562,"ev.rt":447.958644390591,"flagUpdatedRewards":0,"observation_code":6,"observation_description":"sMEC_x_AND_sMR_s_AND_sMP_f","observation_probability":0.3652,"selected_action":"MST","step_reward":38.0,"updated_belief_mec_true_(s')":0.909339324262736,"updated_belief_mp_true_(s')":0.910030750237796,"updated_belief_mr_true_(s')":0.939872845259976},
"11":{"acu_rewards_discounted":355.482698870623,"acu_rewards_undiscounted":464.0,"arrived_mec_state_(s')":1,"arrived_mp_state_(s')":1,"arrived_mr_state_(s')":1,"current_belief_mec_true_(s)":0.909339324262736,"current_belief_mp_true_(s)":0.910030750237796,"current_belief_mr_true_(s)":0.939872845259976,"current_mec_state(s)":1,"current_mp_state(s)":0,"current_mr_state(s)":1,"current_rewards":[[39.0,40.0,38.0,16.0,43.0,28.0,13.0,1.0],[43.0,31.0,28.0,26.0,28.0,16.0,23.0,11.0]],"ev.mst":461.999201566226,"ev.rt":439.121853990203,"flagUpdatedRewards":0,"observation_code":15,"observation_description":"sMEC_x_y_AND_sMR_s_AND_sMP_f","observation_probability":0.09711,"selected_action":"MST","step_reward":39.0,"updated_belief_mec_true_(s')":0.869237623500365,"updated_belief_mp_true_(s')":0.909176505448717,"updated_belief_mr_true_(s')":0.930585157418539},
"12":{"acu_rewards_discounted":376.556742289466,"acu_rewards_undiscounted":503.0,"arrived_mec_state_(s')":1,"arrived_mp_state_(s')":1,"arrived_mr_state_(s')":1,"current_belief_mec_true_(s)":0.869237623500365,"current_belief_mp_true_(s)":0.909176505448717,"current_belief_mr_true_(s)":0.930585157418539,"current_mec_state(s)":1,"current_mp_state(s)":1,"current_mr_state(s)":1,"current_rewards":[[39.0,40.0,38.0,16.0,43.0,28.0,13.0,1.0],[43.0,31.0,28.0,26.0,28.0,16.0,23.0,11.0]],"ev.mst":461.980438640277,"ev.rt":418.410453956795,"flagUpdatedRewards":0,"observation_code":6,"observation_description":"sMEC_x_AND_sMR_s_AND_sMP_f","observation_probability":0.51792,"selected_action":"MST","step_reward":39.0,"updated_belief_mec_true_(s')":0.900373627264393,"updated_belief_mp_true_(s')":0.910695312125359,"updated_belief_mr_true_(s')":0.937630036699027},
"13":{"acu_rewards_discounted":396.577083537367,"acu_rewards_undiscounted":542.0,"arrived_mec_state_(s')":1,"arrived_mp_state_(s')":1,"arrived_mr_state_(s')":1,"current_belief_mec_true_(s)":0.900373627264393,"current_belief_mp_true_(s)":0.910695312125359,"current_belief_mr_true_(s)":0.937630036699027,"current_mec_state(s)":0,"current_mp_state(s)":1,"current_mr_state(s)":1,"current_rewards":[[39.0,40.0,38.0,16.0,43.0,28.0,13.0,1.0],[43.0,31.0,28.0,26.0,28.0,16.0,23.0,11.0]],"ev.mst":466.046186496646,"ev.rt":432.704558828128,"flagUpdatedRewards":0,"observation_code":12,"observation_description":"sMEC_x_y_AND_sMR_r_s_AND_sMP_f","observation_probability":0.01992,"selected_action":"MST","step_reward":39.0,"updated_belief_mec_true_(s')":0.867161703290155,"updated_belief_mp_true_(s')":0.918615404919773,"updated_belief_mr_true_(s')":0.852406943253706},
"14":{"acu_rewards_discounted":415.596407722873,"acu_rewards_undiscounted":581.0,"arrived_mec_state_(s')":1,"arrived_mp_state_(s')":1,"arrived_mr_state_(s')":1,"current_belief_mec_true_(s)":0.867161703290155,"current_belief_mp_true_(s)":0.918615404919773,"current_belief_mr_true_(s)":0.852406943253706,"current_mec_state(s)":1,"current_mp_state(s)":1,"current_mr_state(s)":1,"current_rewards":[[39.0,40.0,38.0,16.0,43.0,28.0,13.0,1.0],[43.0,31.0,28.0,26.0,28.0,16.0,23.0,11.0]],"ev.mst":466.998574052874,"ev.rt":455.994394606837,"flagUpdatedRewards":0,"observation_code":6,"observation_description":"sMEC_x_AND_sMR_s_AND_sMP_f","observation_probability":0.51792,"selected_action":"MST","step_reward":39.0,"updated_belief_mec_true_(s')":0.898721654777407,"updated_belief_mp_true_(s')":0.913347051473622,"updated_belief_mr_true_(s')":0.939568775926716},
"15":{"acu_rewards_discounted":433.664765699103,"acu_rewards_undiscounted":620.0,"arrived_mec_state_(s')":1,"arrived_mp_state_(s')":1,"arrived_mr_state_(s')":1,"current_belief_mec_true_(s)":0.898721654777407,"current_belief_mp_true_(s)":0.913347051473622,"current_belief_mr_true_(s)":0.939568775926716,"current_mec_state(s)":1,"current_mp_state(s)":1,"current_mr_state(s)":0,"current_rewards":[[39.0,40.0,38.0,16.0,43.0,28.0,13.0,1.0],[43.0,31.0,28.0,26.0,28.0,16.0,23.0,11.0]],"ev.mst":474.457006207602,"ev.rt":434.555768940846,"flagUpdatedRewards":0,"observation_code":15,"observation_description":"sMEC_x_y_AND_sMR_s_AND_sMP_f","observation_probability":0.09711,"selected_action":"MST","step_reward":39.0,"updated_belief_mec_true_(s')":0.862419867931131,"updated_belief_mp_true_(s')":0.914246499787264,"updated_belief_mr_true_(s')":0.940583385030148},
"16":{"acu_rewards_discounted":450.829705776522,"acu_rewards_undiscounted":659.0,"arrived_mec_state_(s')":1,"arrived_mp_state_(s')":1,"arrived_mr_state_(s')":1,"current_belief_mec_true_(s)":0.862419867931131,"current_belief_mp_true_(s)":0.914246499787264,"current_belief_mr_true_(s)":0.940583385030148,"current_mec_state(s)":1,"current_mp_state(s)":1,"current_mr_state(s)":1,"current_rewards":[[39.0,40.0,38.0,16.0,43.0,28.0,13.0,1.0],[43.0,31.0,28.0,26.0,28.0,16.0,23.0,11.0]],"ev.mst":457.453071402453,"ev.rt":426.245802219926,"flagUpdatedRewards":0,"observation_code":7,"observation_description":"sMEC_x_AND_sMR_s_AND_sMP_f_g","observation_probability":0.08112,"selected_action":"MST","step_reward":39.0,"updated_belief_mec_true_(s')":0.906028520998227,"updated_belief_mp_true_(s')":0.834299399968309,"updated_belief_mr_true_(s')":0.932727612498029},
"17":{"acu_rewards_discounted":467.13639885007,"acu_rewards_undiscounted":698.0,"arrived_mec_state_(s')":1,"arrived_mp_state_(s')":1,"arrived_mr_state_(s')":1,"current_belief_mec_true_(s)":0.906028520998227,"current_belief_mp_true_(s)":0.834299399968309,"current_belief_mr_true_(s)":0.932727612498029,"current_mec_state(s)":1,"current_mp_state(s)":1,"current_mr_state(s)":1,"current_rewards":[[39.0,40.0,38.0,16.0,43.0,28.0,13.0,1.0],[43.0,31.0,28.0,26.0,28.0,16.0,23.0,11.0]],"ev.mst":465.952657187172,"ev.rt":440.509297246986,"flagUpdatedRewards":0,"observation_code":6,"observation_description":"sMEC_x_AND_sMR_s_AND_sMP_f","observation_probability":0.51792,"selected_action":"MST","step_reward":39.0,"updated_belief_mec_true_(s')":0.914199534336199,"updated_belief_mp_true_(s')":0.911570983779506,"updated_belief_mr_true_(s')":0.937727970402004},
"18":{"acu_rewards_discounted":482.62775726994,"acu_rewards_undiscounted":737.0,"arrived_mec_state_(s')":1,"arrived_mp_state_(s')":1,"arrived_mr_state_(s')":1,"current_belief_mec_true_(s)":0.914199534336199,"current_belief_mp_true_(s)":0.911570983779506,"current_belief_mr_true_(s)":0.937727970402004,"current_mec_state(s)":1,"current_mp_state(s)":1,"current_mr_state(s)":1,"current_rewards":[[39.0,40.0,38.0,16.0,43.0,28.0,13.0,1.0],[43.0,31.0,28.0,26.0,28.0,16.0,23.0,11.0]],"ev.mst":468.486679913395,"ev.rt":446.119727998163,"flagUpdatedRewards":0,"observation_code":15,"observation_description":"sMEC_x_y_AND_sMR_s_AND_sMP_f","observation_probability":0.09711,"selected_action":"MST","step_reward":39.0,"updated_belief_mec_true_(s')":0.86456190009184,"updated_belief_mp_true_(s')":0.913169066953282,"updated_belief_mr_true_(s')":0.933174134895116},
"19":{"acu_rewards_discounted":497.344547768817,"acu_rewards_undiscounted":776.0,"arrived_mec_state_(s')":1,"arrived_mp_state_(s')":1,"arrived_mr_state_(s')":1,"current_belief_mec_true_(s)":0.86456190009184,"current_belief_mp_true_(s)":0.913169066953282,"current_belief_mr_true_(s)":0.933174134895116,"current_mec_state(s)":1,"current_mp_state(s)":1,"current_mr_state(s)":1,"current_rewards":[[39.0,40.0,38.0,16.0,43.0,28.0,13.0,1.0],[43.0,31.0,28.0,26.0,28.0,16.0,23.0,11.0]],"ev.mst":460.722694993917,"ev.rt":434.300376703397,"flagUpdatedRewards":0,"observation_code":6,"observation_description":"sMEC_x_AND_sMR_s_AND_sMP_f","observation_probability":0.51792,"selected_action":"MST","step_reward":39.0,"updated_belief_mec_true_(s')":0.900611209456788,"updated_belief_mp_true_(s')":0.921322396476024,"updated_belief_mr_true_(s')":0.942717411168491},
"20":{"acu_rewards_discounted":511.32549874275,"acu_rewards_undiscounted":815.0,"arrived_mec_state_(s')":1,"arrived_mp_state_(s')":1,"arrived_mr_state_(s')":1,"current_belief_mec_true_(s)":0.900611209456788,"current_belief_mp_true_(s)":0.921322396476024,"current_belief_mr_true_(s)":0.942717411168491,"current_mec_state(s)":1,"current_mp_state(s)":1,"current_mr_state(s)":1,"current_rewards":[[39.0,40.0,38.0,16.0,43.0,28.0,13.0,1.0],[43.0,31.0,28.0,26.0,28.0,16.0,23.0,11.0]],"ev.mst":456.916027641571,"ev.rt":441.016955783114,"flagUpdatedRewards":0,"observation_code":0,"observation_description":"sMEC_x_AND_sMR_r_AND_sMP_f","observation_probability":0.03984,"selected_action":"MST","step_reward":39.0,"updated_belief_mec_true_(s')":0.89990234375,"updated_belief_mp_true_(s')":0.9267578125,"updated_belief_mr_true_(s')":0.830810546875},
"21":{"acu_rewards_discounted":524.607402167987,"acu_rewards_undiscounted":854.0,"arrived_mec_state_(s')":1,"arrived_mp_state_(s')":1,"arrived_mr_state_(s')":1,"current_belief_mec_true_(s)":0.89990234375,"current_belief_mp_true_(s)":0.9267578125,"current_belief_mr_true_(s)":0.830810546875,"current_mec_state(s)":1,"current_mp_state(s)":1,"current_mr_state(s)":1,"current_rewards":[[39.0,40.0,38.0,16.0,43.0,28.0,13.0,1.0],[43.0,31.0,28.0,26.0,28.0,16.0,23.0,11.0]],"ev.mst":469.691682407061,"ev.rt":433.723130420378,"flagUpdatedRewards":0,"observation_code":6,"observation_description":"sMEC_x_AND_sMR_s_AND_sMP_f","observation_probability":0.51792,"selected_action":"MST","step_reward":39.0,"updated_belief_mec_true_(s')":0.903258443822352,"updated_belief_mp_true_(s')":0.910164884553416,"updated_belief_mr_true_(s')":0.92852782402021},
"22":{"acu_rewards_discounted":537.225210421962,"acu_rewards_undiscounted":893.0,"arrived_mec_state_(s')":1,"arrived_mp_state_(s')":1,"arrived_mr_state_(s')":1,"current_belief_mec_true_(s)":0.903258443822352,"current_belief_mp_true_(s)":0.910164884553416,"current_belief_mr_true_(s)":0.92852782402021,"current_mec_state(s)":0,"current_mp_state(s)":0,"current_mr_state(s)":1,"current_rewards":[[39.0,40.0,38.0,16.0,43.0,28.0,13.0,1.0],[43.0,31.0,28.0,26.0,28.0,16.0,23.0,11.0]],"ev.mst":456.653955567568,"ev.rt":449.616303357939,"flagUpdatedRewards":0,"observation_code":6,"observation_description":"sMEC_x_AND_sMR_s_AND_sMP_f","observation_probability":0.51792,"selected_action":"MST","step_reward":39.0,"updated_belief_mec_true_(s')":0.901502598899526,"updated_belief_mp_true_(s')":0.918522221299249,"updated_belief_mr_true_(s')":0.939891891389094},
"23":{"acu_rewards_discounted":546.753273321437,"acu_rewards_undiscounted":924.0,"arrived_mec_state_(s')":1,"arrived_mp_state_(s')":0,"arrived_mr_state_(s')":1,"current_belief_mec_true_(s)":0.901502598899526,"current_belief_mp_true_(s)":0.918522221299249,"current_belief_mr_true_(s)":0.939891891389094,"current_mec_state(s)":1,"current_mp_state(s)":1,"current_mr_state(s)":1,"current_rewards":[[39.0,40.0,38.0,16.0,43.0,28.0,13.0,1.0],[43.0,31.0,28.0,26.0,28.0,16.0,23.0,11.0]],"ev.mst":453.917289938338,"ev.rt":457.378356473236,"flagUpdatedRewards":0,"observation_code":10,"observation_description":"sMEC_x_y_AND_sMR_r_AND_sMP_f_g","observation_probability":0.002,"selected_action":"RT","step_reward":31.0,"updated_belief_mec_true_(s')":0.763150673626847,"updated_belief_mp_true_(s')":0.72540654883895,"updated_belief_mr_true_(s')":0.918485864421183},
"24":{"acu_rewards_discounted":558.140845270649,"acu_rewards_undiscounted":963.0,"arrived_mec_state_(s')":1,"arrived_mp_state_(s')":1,"arrived_mr_state_(s')":1,"current_belief_mec_true_(s)":0.763150673626847,"current_belief_mp_true_(s)":0.72540654883895,"current_belief_mr_true_(s)":0.918485864421183,"current_mec_state(s)":0,"current_mp_state(s)":1,"current_mr_state(s)":1,"current_rewards":[[39.0,40.0,38.0,16.0,43.0,28.0,13.0,1.0],[43.0,31.0,28.0,26.0,28.0,16.0,23.0,11.0]],"ev.mst":457.850243742608,"ev.rt":434.890798805096,"flagUpdatedRewards":0,"observation_code":7,"observation_description":"sMEC_x_AND_sMR_s_AND_sMP_f_g","observation_probability":0.08112,"selected_action":"MST","step_reward":39.0,"updated_belief_mec_true_(s')":0.899155207530968,"updated_belief_mp_true_(s')":0.817453758608571,"updated_belief_mr_true_(s')":0.939271615883355},
"25":{"acu_rewards_discounted":568.959038622401,"acu_rewards_undiscounted":1002.0,"arrived_mec_state_(s')":1,"arrived_mp_state_(s')":1,"arrived_mr_state_(s')":1,"current_belief_mec_true_(s)":0.899155207530968,"current_belief_mp_true_(s)":0.817453758608571,"current_belief_mr_true_(s)":0.939271615883355,"current_mec_state(s)":1,"current_mp_state(s)":0,"current_mr_state(s)":1,"current_rewards":[[39.0,40.0,38.0,16.0,43.0,28.0,13.0,1.0],[43.0,31.0,28.0,26.0,28.0,16.0,23.0,11.0]],"ev.mst":458.125269630081,"ev.rt":450.997876020512,"flagUpdatedRewards":0,"observation_code":3,"observation_description":"sMEC_x_AND_sMR_r_s_AND_sMP_f","observation_probability":0.10624,"selected_action":"MST","step_reward":39.0,"updated_belief_mec_true_(s')":0.906562042613014,"updated_belief_mp_true_(s')":0.908033842479521,"updated_belief_mr_true_(s')":0.856056076400796},
"26":{"acu_rewards_discounted":579.236322306565,"acu_rewards_undiscounted":1041.0,"arrived_mec_state_(s')":1,"arrived_mp_state_(s')":1,"arrived_mr_state_(s')":1,"current_belief_mec_true_(s)":0.906562042613014,"current_belief_mp_true_(s)":0.908033842479521,"current_belief_mr_true_(s)":0.856056076400796,"current_mec_state(s)":1,"current_mp_state(s)":1,"current_mr_state(s)":1,"current_rewards":[[39.0,40.0,38.0,16.0,43.0,28.0,13.0,1.0],[43.0,31.0,28.0,26.0,28.0,16.0,23.0,11.0]],"ev.mst":457.446234279136,"ev.rt":452.101426946798,"flagUpdatedRewards":0,"observation_code":7,"observation_description":"sMEC_x_AND_sMR_s_AND_sMP_f_g","observation_probability":0.08112,"selected_action":"MST","step_reward":39.0,"updated_belief_mec_true_(s')":0.906651871507516,"updated_belief_mp_true_(s')":0.825779530683414,"updated_belief_mr_true_(s')":0.937474924632849},
"27":{"acu_rewards_discounted":588.999741806521,"acu_rewards_undiscounted":1080.0,"arrived_mec_state_(s')":1,"arrived_mp_state_(s')":1,"arrived_mr_state_(s')":1,"current_belief_mec_true_(s)":0.906651871507516,"current_belief_mp_true_(s)":0.825779530683414,"current_belief_mr_true_(s)":0.937474924632849,"current_mec_state(s)":1,"current_mp_state(s)":1,"current_mr_state(s)":1,"current_rewards":[[39.0,40.0,38.0,16.0,43.0,28.0,13.0,1.0],[43.0,31.0,28.0,26.0,28.0,16.0,23.0,11.0]],"ev.mst":458.293679750423,"ev.rt":442.724369484378,"flagUpdatedRewards":0,"observation_code":6,"observation_description":"sMEC_x_AND_sMR_s_AND_sMP_f","observation_probability":0.51792,"selected_action":"MST","step_reward":39.0,"updated_belief_mec_true_(s')":0.899081507594995,"updated_belief_mp_true_(s')":0.909553943801788,"updated_belief_mr_true_(s')":0.934381096333983},
"28":{"acu_rewards_discounted":598.274990331479,"acu_rewards_undiscounted":1119.0,"arrived_mec_state_(s')":1,"arrived_mp_state_(s')":1,"arrived_mr_state_(s')":1,"current_belief_mec_true_(s)":0.899081507594995,"current_belief_mp_true_(s)":0.909553943801788,"current_belief_mr_true_(s)":0.934381096333983,"current_mec_state(s)":1,"current_mp_state(s)":0,"current_mr_state(s)":1,"current_rewards":[[39.0,40.0,38.0,16.0,43.0,28.0,13.0,1.0],[43.0,31.0,28.0,26.0,28.0,16.0,23.0,11.0]],"ev.mst":463.296425717489,"ev.rt":461.857986457733,"flagUpdatedRewards":0,"observation_code":7,"observation_description":"sMEC_x_AND_sMR_s_AND_sMP_f_g","observation_probability":0.08112,"selected_action":"MST","step_reward":39.0,"updated_belief_mec_true_(s')":0.900554910685848,"updated_belief_mp_true_(s')":0.814072176568527,"updated_belief_mr_true_(s')":0.94151161395768},
"29":{"acu_rewards_discounted":601.88995898736,"acu_rewards_undiscounted":1135.0,"arrived_mec_state_(s')":1,"arrived_mp_state_(s')":0,"arrived_mr_state_(s')":0,"current_belief_mec_true_(s)":0.900554910685848,"current_belief_mp_true_(s)":0.814072176568527,"current_belief_mr_true_(s)":0.94151161395768,"current_mec_state(s)":1,"current_mp_state(s)":1,"current_mr_state(s)":1,"current_rewards":[[39.0,40.0,38.0,16.0,43.0,28.0,13.0,1.0],[43.0,31.0,28.0,26.0,28.0,16.0,23.0,11.0]],"ev.mst":456.478664598369,"ev.rt":448.48275146922,"flagUpdatedRewards":0,"observation_code":8,"observation_description":"sMEC_x_AND_sMR_s_AND_sMP_g","observation_probability":0.044,"selected_action":"MST","step_reward":16.0,"updated_belief_mec_true_(s')":0.906958218225664,"updated_belief_mp_true_(s')":0.746309938183389,"updated_belief_mr_true_(s')":0.939562857626233},
"30":{"acu_rewards_discounted":610.046232017191,"acu_rewards_undiscounted":1173.0,"arrived_mec_state_(s')":1,"arrived_mp_state_(s')":1,"arrived_mr_state_(s')":0,"current_belief_mec_true_(s)":0.906958218225664,"current_belief_mp_true_(s)":0.746309938183389,"current_belief_mr_true_(s)":0.939562857626233,"current_mec_state(s)":1,"current_mp_state(s)":1,"current_mr_state(s)":1,"current_rewards":[[39.0,40.0,38.0,16.0,43.0,28.0,13.0,1.0],[43.0,31.0,28.0,26.0,28.0,16.0,23.0,11.0]],"ev.mst":465.826891581939,"ev.rt":447.35919439452,"flagUpdatedRewards":0,"observation_code":6,"observation_description":"sMEC_x_AND_sMR_s_AND_sMP_f","observation_probability":0.3652,"selected_action":"MST","step_reward":38.0,"updated_belief_mec_true_(s')":0.898487258718274,"updated_belief_mp_true_(s')":0.905343573041939,"updated_belief_mr_true_(s')":0.928067847200223},
"31":{"acu_rewards_discounted":617.998598221277,"acu_rewards_undiscounted":1212.0,"arrived_mec_state_(s')":1,"arrived_mp_state_(s')":1,"arrived_mr_state_(s')":1,"current_belief_mec_true_(s)":0.898487258718274,"current_belief_mp_true_(s)":0.905343573041939,"current_belief_mr_true_(s)":0.928067847200223,"current_mec_state(s)":1,"current_mp_state(s)":1,"current_mr_state(s)":1,"current_rewards":[[39.0,40.0,38.0,16.0,43.0,28.0,13.0,1.0],[43.0,31.0,28.0,26.0,28.0,16.0,23.0,11.0]],"ev.mst":462.194133293789,"ev.rt":448.700618513082,"flagUpdatedRewards":0,"observation_code":24,"observation_description":"sMEC_y_AND_sMR_s_AND_sMP_f","observation_probability":0.03237,"selected_action":"MST","step_reward":39.0,"updated_belief_mec_true_(s')":0.810698525367282,"updated_belief_mp_true_(s')":0.911385228772205,"updated_belief_mr_true_(s')":0.935869084080738},
"32":{"acu_rewards_discounted":626.328192052993,"acu_rewards_undiscounted":1255.0,"arrived_mec_state_(s')":1,"arrived_mp_state_(s')":1,"arrived_mr_state_(s')":1,"current_belief_mec_true_(s)":0.810698525367282,"current_belief_mp_true_(s)":0.911385228772205,"current_belief_mr_true_(s)":0.935869084080738,"current_mec_state(s)":1,"current_mp_state(s)":1,"current_mr_state(s)":1,"current_rewards":[[39.0,40.0,38.0,16.0,43.0,28.0,13.0,1.0],[43.0,31.0,28.0,26.0,28.0,16.0,23.0,11.0]],"ev.mst":459.935909905067,"ev.rt":461.154086963056,"flagUpdatedRewards":0,"observation_code":0,"observation_description":"sMEC_x_AND_sMR_r_AND_sMP_f","observation_probability":0.0312,"selected_action":"RT","step_reward":43.0,"updated_belief_mec_true_(s')":0.87109375,"updated_belief_mp_true_(s')":0.8388671875,"updated_belief_mr_true_(s')":0.920166015625},
"33":{"acu_rewards_discounted":634.241306193122,"acu_rewards_undiscounted":1298.0,"arrived_mec_state_(s')":0,"arrived_mp_state_(s')":1,"arrived_mr_state_(s')":1,"current_belief_mec_true_(s)":0.87109375,"current_belief_mp_true_(s)":0.8388671875,"current_belief_mr_true_(s)":0.920166015625,"current_mec_state(s)":1,"current_mp_state(s)":1,"current_mr_state(s)":1,"current_rewards":[[39.0,40.0,38.0,16.0,43.0,28.0,13.0,1.0],[43.0,31.0,28.0,26.0,28.0,16.0,23.0,11.0]],"ev.mst":456.628041502642,"ev.rt":450.203799297995,"flagUpdatedRewards":0,"observation_code":15,"observation_description":"sMEC_x_y_AND_sMR_s_AND_sMP_f","observation_probability":0.116532,"selected_action":"MST","step_reward":43.0,"updated_belief_mec_true_(s')":0.865744202501699,"updated_belief_mp_true_(s')":0.913085544325805,"updated_belief_mr_true_(s')":0.937518833618083},
"34":{"acu_rewards_discounted":641.05946616735,"acu_rewards_undiscounted":1337.0,"arrived_mec_state_(s')":1,"arrived_mp_state_(s')":1,"arrived_mr_state_(s')":1,"current_belief_mec_true_(s)":0.865744202501699,"current_belief_mp_true_(s)":0.913085544325805,"current_belief_mr_true_(s)":0.937518833618083,"current_mec_state(s)":1,"current_mp_state(s)":0,"current_mr_state(s)":1,"current_rewards":[[39.0,40.0,38.0,16.0,43.0,28.0,13.0,1.0],[43.0,31.0,28.0,26.0,28.0,16.0,23.0,11.0]],"ev.mst":475.814037446622,"ev.rt":437.205736782787,"flagUpdatedRewards":0,"observation_code":6,"observation_description":"sMEC_x_AND_sMR_s_AND_sMP_f","observation_probability":0.51792,"selected_action":"MST","step_reward":39.0,"updated_belief_mec_true_(s')":0.894834632263087,"updated_belief_mp_true_(s')":0.911675750345165,"updated_belief_mr_true_(s')":0.935769312987291},
"35":{"acu_rewards_discounted":647.536718142867,"acu_rewards_undiscounted":1376.0,"arrived_mec_state_(s')":1,"arrived_mp_state_(s')":1,"arrived_mr_state_(s')":1,"current_belief_mec_true_(s)":0.894834632263087,"current_belief_mp_true_(s)":0.911675750345165,"current_belief_mr_true_(s)":0.935769312987291,"current_mec_state(s)":1,"current_mp_state(s)":1,"current_mr_state(s)":1,"current_rewards":[[39.0,40.0,38.0,16.0,43.0,28.0,13.0,1.0],[43.0,31.0,28.0,26.0,28.0,16.0,23.0,11.0]],"ev.mst":458.156986072902,"ev.rt":432.074860076072,"flagUpdatedRewards":0,"observation_code":0,"observation_description":"sMEC_x_AND_sMR_r_AND_sMP_f","observation_probability":0.03984,"selected_action":"MST","step_reward":39.0,"updated_belief_mec_true_(s')":0.900631682114264,"updated_belief_mp_true_(s')":0.91638512215523,"updated_belief_mr_true_(s')":0.835560475339733},
"36":{"acu_rewards_discounted":653.690107519608,"acu_rewards_undiscounted":1415.0,"arrived_mec_state_(s')":1,"arrived_mp_state_(s')":1,"arrived_mr_state_(s')":1,"current_belief_mec_true_(s)":0.900631682114264,"current_belief_mp_true_(s)":0.91638512215523,"current_belief_mr_true_(s)":0.835560475339733,"current_mec_state(s)":1,"current_mp_state(s)":1,"current_mr_state(s)":0,"current_rewards":[[39.0,40.0,38.0,16.0,43.0,28.0,13.0,1.0],[43.0,31.0,28.0,26.0,28.0,16.0,23.0,11.0]],"ev.mst":457.89648791399,"ev.rt":453.021645911117,"flagUpdatedRewards":0,"observation_code":6,"observation_description":"sMEC_x_AND_sMR_s_AND_sMP_f","observation_probability":0.51792,"selected_action":"MST","step_reward":39.0,"updated_belief_mec_true_(s')":0.904980999014421,"updated_belief_mp_true_(s')":0.918698767582988,"updated_belief_mr_true_(s')":0.938167821220492},
"37":{"acu_rewards_discounted":659.535827427512,"acu_rewards_undiscounted":1454.0,"arrived_mec_state_(s')":1,"arrived_mp_state_(s')":1,"arrived_mr_state_(s')":1,"current_belief_mec_true_(s)":0.904980999014421,"current_belief_mp_true_(s)":0.918698767582988,"current_belief_mr_true_(s)":0.938167821220492,"current_mec_state(s)":1,"current_mp_state(s)":1,"current_mr_state(s)":1,"current_rewards":[[39.0,40.0,38.0,16.0,43.0,28.0,13.0,1.0],[43.0,31.0,28.0,26.0,28.0,16.0,23.0,11.0]],"ev.mst":476.242343375348,"ev.rt":444.142971477691,"flagUpdatedRewards":0,"observation_code":6,"observation_description":"sMEC_x_AND_sMR_s_AND_sMP_f","observation_probability":0.51792,"selected_action":"MST","step_reward":39.0,"updated_belief_mec_true_(s')":0.910005255731146,"updated_belief_mp_true_(s')":0.913564309711307,"updated_belief_mr_true_(s')":0.933729689926126},
"38":{"acu_rewards_discounted":665.08926134002,"acu_rewards_undiscounted":1493.0,"arrived_mec_state_(s')":1,"arrived_mp_state_(s')":1,"arrived_mr_state_(s')":1,"current_belief_mec_true_(s)":0.910005255731146,"current_belief_mp_true_(s)":0.913564309711307,"current_belief_mr_true_(s)":0.933729689926126,"current_mec_state(s)":1,"current_mp_state(s)":1,"current_mr_state(s)":1,"current_rewards":[[39.0,40.0,38.0,16.0,43.0,28.0,13.0,1.0],[43.0,31.0,28.0,26.0,28.0,16.0,23.0,11.0]],"ev.mst":459.255694675005,"ev.rt":434.380625832729,"flagUpdatedRewards":0,"observation_code":6,"observation_description":"sMEC_x_AND_sMR_s_AND_sMP_f","observation_probability":0.51792,"selected_action":"MST","step_reward":39.0,"updated_belief_mec_true_(s')":0.90857429427651,"updated_belief_mp_true_(s')":0.911036194867711,"updated_belief_mr_true_(s')":0.941836429100975},
"39":{"acu_rewards_discounted":670.365023556904,"acu_rewards_undiscounted":1532.0,"arrived_mec_state_(s')":1,"arrived_mp_state_(s')":1,"arrived_mr_state_(s')":1,"current_belief_mec_true_(s)":0.90857429427651,"current_belief_mp_true_(s)":0.911036194867711,"current_belief_mr_true_(s)":0.941836429100975,"current_mec_state(s)":1,"current_mp_state(s)":1,"current_mr_state(s)":1,"current_rewards":[[39.0,40.0,38.0,16.0,43.0,28.0,13.0,1.0],[43.0,31.0,28.0,26.0,28.0,16.0,23.0,11.0]],"ev.mst":462.152016640525,"ev.rt":450.65298323869,"flagUpdatedRewards":0,"observation_code":6,"observation_description":"sMEC_x_AND_sMR_s_AND_sMP_f","observation_probability":0.51792,"selected_action":"MST","step_reward":39.0,"updated_belief_mec_true_(s')":0.904831912809859,"updated_belief_mp_true_(s')":0.914589662319903,"updated_belief_mr_true_(s')":0.937539661748712},
"40":{"acu_rewards_discounted":675.376997662943,"acu_rewards_undiscounted":1571.0,"arrived_mec_state_(s')":1,"arrived_mp_state_(s')":1,"arrived_mr_state_(s')":1,"current_belief_mec_true_(s)":0.904831912809859,"current_belief_mp_true_(s)":0.914589662319903,"current_belief_mr_true_(s)":0.937539661748712,"current_mec_state(s)":1,"current_mp_state(s)":1,"current_mr_state(s)":1,"current_rewards":[[39.0,40.0,38.0,16.0,43.0,28.0,13.0,1.0],[43.0,31.0,28.0,26.0,28.0,16.0,23.0,11.0]],"ev.mst":460.088300284767,"ev.rt":443.909740078134,"flagUpdatedRewards":0,"observation_code":6,"observation_description":"sMEC_x_AND_sMR_s_AND_sMP_f","observation_probability":0.51792,"selected_action":"MST","step_reward":39.0,"updated_belief_mec_true_(s')":0.906473460470546,"updated_belief_mp_true_(s')":0.908088166203501,"updated_belief_mr_true_(s')":0.931410633726795},
"41":{"acu_rewards_discounted":680.13837306368,"acu_rewards_undiscounted":1610.0,"arrived_mec_state_(s')":1,"arrived_mp_state_(s')":1,"arrived_mr_state_(s')":1,"current_belief_mec_true_(s)":0.906473460470546,"current_belief_mp_true_(s)":0.908088166203501,"current_belief_mr_true_(s)":0.931410633726795,"current_mec_state(s)":1,"current_mp_state(s)":1,"current_mr_state(s)":1,"current_rewards":[[39.0,40.0,38.0,16.0,43.0,28.0,13.0,1.0],[43.0,31.0,28.0,26.0,28.0,16.0,23.0,11.0]],"ev.mst":458.076841076164,"ev.rt":442.083610805831,"flagUpdatedRewards":0,"observation_code":6,"observation_description":"sMEC_x_AND_sMR_s_AND_sMP_f","observation_probability":0.51792,"selected_action":"MST","step_reward":39.0,"updated_belief_mec_true_(s')":0.899088773036255,"updated_belief_mp_true_(s')":0.912523512627592,"updated_belief_mr_true_(s')":0.935908229822211},
"42":{"acu_rewards_discounted":684.54569747308,"acu_rewards_undiscounted":1648.0,"arrived_mec_state_(s')":1,"arrived_mp_state_(s')":1,"arrived_mr_state_(s')":0,"current_belief_mec_true_(s)":0.899088773036255,"current_belief_mp_true_(s)":0.912523512627592,"current_belief_mr_true_(s)":0.935908229822211,"current_mec_state(s)":1,"current_mp_state(s)":1,"current_mr_state(s)":1,"current_rewards":[[39.0,40.0,38.0,16.0,43.0,28.0,13.0,1.0],[43.0,31.0,28.0,26.0,28.0,16.0,23.0,11.0]],"ev.mst":458.819958193608,"ev.rt":438.419247063886,"flagUpdatedRewards":0,"observation_code":24,"observation_description":"sMEC_y_AND_sMR_s_AND_sMP_f","observation_probability":0.022825,"selected_action":"MST","step_reward":38.0,"updated_belief_mec_true_(s')":0.808728320015441,"updated_belief_mp_true_(s')":0.916235108275217,"updated_belief_mr_true_(s')":0.936452968711114},
"43":{"acu_rewards_discounted":689.283571213185,"acu_rewards_undiscounted":1691.0,"arrived_mec_state_(s')":0,"arrived_mp_state_(s')":1,"arrived_mr_state_(s')":1,"current_belief_mec_true_(s)":0.808728320015441,"current_belief_mp_true_(s)":0.916235108275217,"current_belief_mr_true_(s)":0.936452968711114,"current_mec_state(s)":1,"current_mp_state(s)":1,"current_mr_state(s)":1,"current_rewards":[[39.0,40.0,38.0,16.0,43.0,28.0,13.0,1.0],[43.0,31.0,28.0,26.0,28.0,16.0,23.0,11.0]],"ev.mst":471.340168374975,"ev.rt":449.84940739029,"flagUpdatedRewards":0,"observation_code":24,"observation_description":"sMEC_y_AND_sMR_s_AND_sMP_f","observation_probability":0.06474,"selected_action":"MST","step_reward":43.0,"updated_belief_mec_true_(s')":0.785515739964053,"updated_belief_mp_true_(s')":0.90470620810354,"updated_belief_mr_true_(s')":0.942254622283984},
"44":{"acu_rewards_discounted":693.365855447392,"acu_rewards_undiscounted":1730.0,"arrived_mec_state_(s')":1,"arrived_mp_state_(s')":1,"arrived_mr_state_(s')":1,"current_belief_mec_true_(s)":0.785515739964053,"current_belief_mp_true_(s)":0.90470620810354,"current_belief_mr_true_(s)":0.942254622283984,"current_mec_state(s)":1,"current_mp_state(s)":1,"current_mr_state(s)":1,"current_rewards":[[39.0,40.0,38.0,16.0,43.0,28.0,13.0,1.0],[43.0,31.0,28.0,26.0,28.0,16.0,23.0,11.0]],"ev.mst":472.398344800724,"ev.rt":450.043707947523,"flagUpdatedRewards":0,"observation_code":6,"observation_description":"sMEC_x_AND_sMR_s_AND_sMP_f","observation_probability":0.51792,"selected_action":"MST","step_reward":39.0,"updated_belief_mec_true_(s')":0.88942494642546,"updated_belief_mp_true_(s')":0.919234354901223,"updated_belief_mr_true_(s')":0.935316730140371},
"45":{"acu_rewards_discounted":697.244025469889,"acu_rewards_undiscounted":1769.0,"arrived_mec_state_(s')":1,"arrived_mp_state_(s')":1,"arrived_mr_state_(s')":1,"current_belief_mec_true_(s)":0.88942494642546,"current_belief_mp_true_(s)":0.919234354901223,"current_belief_mr_true_(s)":0.935316730140371,"current_mec_state(s)":1,"current_mp_state(s)":1,"current_mr_state(s)":1,"current_rewards":[[39.0,40.0,38.0,16.0,43.0,28.0,13.0,1.0],[43.0,31.0,28.0,26.0,28.0,16.0,23.0,11.0]],"ev.mst":466.149518430032,"ev.rt":452.632502851458,"flagUpdatedRewards":0,"observation_code":6,"observation_description":"sMEC_x_AND_sMR_s_AND_sMP_f","observation_probability":0.51792,"selected_action":"MST","step_reward":39.0,"updated_belief_mec_true_(s')":0.902545372364432,"updated_belief_mp_true_(s')":0.910780890287219,"updated_belief_mr_true_(s')":0.927946476547809},
"46":{"acu_rewards_discounted":701.022755235398,"acu_rewards_undiscounted":1809.0,"arrived_mec_state_(s')":1,"arrived_mp_state_(s')":0,"arrived_mr_state_(s')":1,"current_belief_mec_true_(s)":0.902545372364432,"current_belief_mp_true_(s)":0.910780890287219,"current_belief_mr_true_(s)":0.927946476547809,"current_mec_state(s)":1,"current_mp_state(s)":1,"current_mr_state(s)":0,"current_rewards":[[39.0,40.0,38.0,16.0,43.0,28.0,13.0,1.0],[43.0,31.0,28.0,26.0,28.0,16.0,23.0,11.0]],"ev.mst":461.891542360126,"ev.rt":429.204706815779,"flagUpdatedRewards":0,"observation_code":7,"observation_description":"sMEC_x_AND_sMR_s_AND_sMP_f_g","observation_probability":0.14352,"selected_action":"MST","step_reward":40.0,"updated_belief_mec_true_(s')":0.898230641665241,"updated_belief_mp_true_(s')":0.823478272333001,"updated_belief_mr_true_(s')":0.937115652018788},
"47":{"acu_rewards_discounted":704.522803680701,"acu_rewards_undiscounted":1848.0,"arrived_mec_state_(s')":1,"arrived_mp_state_(s')":1,"arrived_mr_state_(s')":1,"current_belief_mec_true_(s)":0.898230641665241,"current_belief_mp_true_(s)":0.823478272333001,"current_belief_mr_true_(s)":0.937115652018788,"current_mec_state(s)":1,"current_mp_state(s)":1,"current_mr_state(s)":1,"current_rewards":[[39.0,40.0,38.0,16.0,43.0,28.0,13.0,1.0],[43.0,31.0,28.0,26.0,28.0,16.0,23.0,11.0]],"ev.mst":459.715156939196,"ev.rt":434.304012119774,"flagUpdatedRewards":0,"observation_code":6,"observation_description":"sMEC_x_AND_sMR_s_AND_sMP_f","observation_probability":0.51792,"selected_action":"MST","step_reward":39.0,"updated_belief_mec_true_(s')":0.903750073469826,"updated_belief_mp_true_(s')":0.914395126263589,"updated_belief_mr_true_(s')":0.936334894712511},
"48":{"acu_rewards_discounted":707.933107294074,"acu_rewards_undiscounted":1888.0,"arrived_mec_state_(s')":1,"arrived_mp_state_(s')":0,"arrived_mr_state_(s')":1,"current_belief_mec_true_(s)":0.903750073469826,"current_belief_mp_true_(s)":0.914395126263589,"current_belief_mr_true_(s)":0.936334894712511,"current_mec_state(s)":1,"current_mp_state(s)":1,"current_mr_state(s)":1,"current_rewards":[[39.0,40.0,38.0,16.0,43.0,28.0,13.0,1.0],[43.0,31.0,28.0,26.0,28.0,16.0,23.0,11.0]],"ev.mst":466.220230467865,"ev.rt":448.926462466101,"flagUpdatedRewards":0,"observation_code":0,"observation_description":"sMEC_x_AND_sMR_r_AND_sMP_f","observation_probability":0.03216,"selected_action":"MST","step_reward":40.0,"updated_belief_mec_true_(s')":0.904793167289826,"updated_belief_mp_true_(s')":0.923978320764019,"updated_belief_mr_true_(s')":0.831407080019232},
"49":{"acu_rewards_discounted":711.09190101596,"acu_rewards_undiscounted":1927.0,"arrived_mec_state_(s')":1,"arrived_mp_state_(s')":1,"arrived_mr_state_(s')":1,"current_belief_mec_true_(s)":0.904793167289826,"current_belief_mp_true_(s)":0.923978320764019,"current_belief_mr_true_(s)":0.831407080019232,"current_mec_state(s)":1,"current_mp_state(s)":1,"current_mr_state(s)":1,"current_rewards":[[39.0,40.0,38.0,16.0,43.0,28.0,13.0,1.0],[43.0,31.0,28.0,26.0,28.0,16.0,23.0,11.0]],"ev.mst":458.214227847379,"ev.rt":449.568110934536,"flagUpdatedRewards":0,"observation_code":24,"observation_description":"sMEC_y_AND_sMR_s_AND_sMP_f","observation_probability":0.03237,"selected_action":"MST","step_reward":39.0,"updated_belief_mec_true_(s')":0.824418078503626,"updated_belief_mp_true_(s')":0.912449790486916,"updated_belief_mr_true_(s')":0.939574647496156},
"50":{"acu_rewards_discounted":714.092755051752,"acu_rewards_undiscounted":1966.0,"arrived_mec_state_(s')":1,"arrived_mp_state_(s')":1,"arrived_mr_state_(s')":1,"current_belief_mec_true_(s)":0.824418078503626,"current_belief_mp_true_(s)":0.912449790486916,"current_belief_mr_true_(s)":0.939574647496156,"current_mec_state(s)":1,"current_mp_state(s)":1,"current_mr_state(s)":0,"current_rewards":[[39.0,40.0,38.0,16.0,43.0,28.0,13.0,1.0],[43.0,31.0,28.0,26.0,28.0,16.0,23.0,11.0]],"ev.mst":457.757206989429,"ev.rt":431.726504646546,"flagUpdatedRewards":0,"observation_code":6,"observation_description":"sMEC_x_AND_sMR_s_AND_sMP_f","observation_probability":0.51792,"selected_action":"MST","step_reward":39.0,"updated_belief_mec_true_(s')":0.91108846399822,"updated_belief_mp_true_(s')":0.916023024592665,"updated_belief_mr_true_(s')":0.933103162668486},
"51":{"acu_rewards_discounted":716.870468659241,"acu_rewards_undiscounted":2004.0,"arrived_mec_state_(s')":1,"arrived_mp_state_(s')":1,"arrived_mr_state_(s')":0,"current_belief_mec_true_(s)":0.91108846399822,"current_belief_mp_true_(s)":0.916023024592665,"current_belief_mr_true_(s)":0.933103162668486,"current_mec_state(s)":1,"current_mp_state(s)":1,"current_mr_state(s)":1,"current_rewards":[[39.0,40.0,38.0,16.0,43.0,28.0,13.0,1.0],[43.0,31.0,28.0,26.0,28.0,16.0,23.0,11.0]],"ev.mst":464.024033627075,"ev.rt":444.103718538278,"flagUpdatedRewards":0,"observation_code":6,"observation_description":"sMEC_x_AND_sMR_s_AND_sMP_f","observation_probability":0.3652,"selected_action":"MST","step_reward":38.0,"updated_belief_mec_true_(s')":0.904439566281831,"updated_belief_mp_true_(s')":0.912937055207891,"updated_belief_mr_true_(s')":0.934235687546511},
"52":{"acu_rewards_discounted":719.509296586356,"acu_rewards_undiscounted":2042.0,"arrived_mec_state_(s')":1,"arrived_mp_state_(s')":1,"arrived_mr_state_(s')":0,"current_belief_mec_true_(s)":0.904439566281831,"current_belief_mp_true_(s)":0.912937055207891,"current_belief_mr_true_(s)":0.934235687546511,"current_mec_state(s)":1,"current_mp_state(s)":1,"current_mr_state(s)":1,"current_rewards":[[39.0,40.0,38.0,16.0,43.0,28.0,13.0,1.0],[43.0,31.0,28.0,26.0,28.0,16.0,23.0,11.0]],"ev.mst":459.177729935174,"ev.rt":442.624026376376,"flagUpdatedRewards":0,"observation_code":6,"observation_description":"sMEC_x_AND_sMR_s_AND_sMP_f","observation_probability":0.3652,"selected_action":"MST","step_reward":38.0,"updated_belief_mec_true_(s')":0.898899662479572,"updated_belief_mp_true_(s')":0.916900570522925,"updated_belief_mr_true_(s')":0.937750785438654},
"53":{"acu_rewards_discounted":722.082153815293,"acu_rewards_undiscounted":2081.0,"arrived_mec_state_(s')":1,"arrived_mp_state_(s')":1,"arrived_mr_state_(s')":1,"current_belief_mec_true_(s)":0.898899662479572,"current_belief_mp_true_(s)":0.916900570522925,"current_belief_mr_true_(s)":0.937750785438654,"current_mec_state(s)":1,"current_mp_state(s)":1,"current_mr_state(s)":1,"current_rewards":[[39.0,40.0,38.0,16.0,43.0,28.0,13.0,1.0],[43.0,31.0,28.0,26.0,28.0,16.0,23.0,11.0]],"ev.mst":457.278907914828,"ev.rt":452.510969488633,"flagUpdatedRewards":0,"observation_code":6,"observation_description":"sMEC_x_AND_sMR_s_AND_sMP_f","observation_probability":0.51792,"selected_action":"MST","step_reward":39.0,"updated_belief_mec_true_(s')":0.910556626458946,"updated_belief_mp_true_(s')":0.909464504852936,"updated_belief_mr_true_(s')":0.931739603994215},
"54":{"acu_rewards_discounted":724.526368182783,"acu_rewards_undiscounted":2120.0,"arrived_mec_state_(s')":1,"arrived_mp_state_(s')":1,"arrived_mr_state_(s')":1,"current_belief_mec_true_(s)":0.910556626458946,"current_belief_mp_true_(s)":0.909464504852936,"current_belief_mr_true_(s)":0.931739603994215,"current_mec_state(s)":1,"current_mp_state(s)":1,"current_mr_state(s)":1,"current_rewards":[[39.0,40.0,38.0,16.0,43.0,28.0,13.0,1.0],[43.0,31.0,28.0,26.0,28.0,16.0,23.0,11.0]],"ev.mst":448.162583185391,"ev.rt":444.052384085773,"flagUpdatedRewards":0,"observation_code":6,"observation_description":"sMEC_x_AND_sMR_s_AND_sMP_f","observation_probability":0.51792,"selected_action":"MST","step_reward":39.0,"updated_belief_mec_true_(s')":0.90408884822463,"updated_belief_mp_true_(s')":0.90443615567459,"updated_belief_mr_true_(s')":0.930839360018851},
"55":{"acu_rewards_discounted":727.086526052321,"acu_rewards_undiscounted":2163.0,"arrived_mec_state_(s')":0,"arrived_mp_state_(s')":1,"arrived_mr_state_(s')":1,"current_belief_mec_true_(s)":0.90408884822463,"current_belief_mp_true_(s)":0.90443615567459,"current_belief_mr_true_(s)":0.930839360018851,"current_mec_state(s)":1,"current_mp_state(s)":0,"current_mr_state(s)":1,"current_rewards":[[39.0,40.0,38.0,16.0,43.0,28.0,13.0,1.0],[43.0,31.0,28.0,26.0,28.0,16.0,23.0,11.0]],"ev.mst":458.291669101215,"ev.rt":440.538794405673,"flagUpdatedRewards":0,"observation_code":6,"observation_description":"sMEC_x_AND_sMR_s_AND_sMP_f","observation_probability":0.466128,"selected_action":"MST","step_reward":43.0,"updated_belief_mec_true_(s')":0.894662521076179,"updated_belief_mp_true_(s')":0.90827022688579,"updated_belief_mr_true_(s')":0.933663228784149},
"56":{"acu_rewards_discounted":729.348991146331,"acu_rewards_undiscounted":2203.0,"arrived_mec_state_(s')":1,"arrived_mp_state_(s')":0,"arrived_mr_state_(s')":1,"current_belief_mec_true_(s)":0.894662521076179,"current_belief_mp_true_(s)":0.90827022688579,"current_belief_mr_true_(s)":0.933663228784149,"current_mec_state(s)":1,"current_mp_state(s)":0,"current_mr_state(s)":1,"current_rewards":[[39.0,40.0,38.0,16.0,43.0,28.0,13.0,1.0],[43.0,31.0,28.0,26.0,28.0,16.0,23.0,11.0]],"ev.mst":466.654011721954,"ev.rt":440.123908618314,"flagUpdatedRewards":0,"observation_code":24,"observation_description":"sMEC_y_AND_sMR_s_AND_sMP_f","observation_probability":0.02613,"selected_action":"MST","step_reward":40.0,"updated_belief_mec_true_(s')":0.811332759071877,"updated_belief_mp_true_(s')":0.908109375972925,"updated_belief_mr_true_(s')":0.94646983389899},
"57":{"acu_rewards_discounted":731.49833298564,"acu_rewards_undiscounted":2243.0,"arrived_mec_state_(s')":1,"arrived_mp_state_(s')":0,"arrived_mr_state_(s')":1,"current_belief_mec_true_(s)":0.811332759071877,"current_belief_mp_true_(s)":0.908109375972925,"current_belief_mr_true_(s)":0.94646983389899,"current_mec_state(s)":0,"current_mp_state(s)":1,"current_mr_state(s)":1,"current_rewards":[[39.0,40.0,38.0,16.0,43.0,28.0,13.0,1.0],[43.0,31.0,28.0,26.0,28.0,16.0,23.0,11.0]],"ev.mst":462.423816809581,"ev.rt":450.367487406996,"flagUpdatedRewards":0,"observation_code":6,"observation_description":"sMEC_x_AND_sMR_s_AND_sMP_f","observation_probability":0.41808,"selected_action":"MST","step_reward":40.0,"updated_belief_mec_true_(s')":0.888580933488879,"updated_belief_mp_true_(s')":0.911247441552795,"updated_belief_mr_true_(s')":0.934295141617396},
"58":{"acu_rewards_discounted":733.489160864301,"acu_rewards_undiscounted":2282.0,"arrived_mec_state_(s')":1,"arrived_mp_state_(s')":1,"arrived_mr_state_(s')":1,"current_belief_mec_true_(s)":0.888580933488879,"current_belief_mp_true_(s)":0.911247441552795,"current_belief_mr_true_(s)":0.934295141617396,"current_mec_state(s)":1,"current_mp_state(s)":1,"current_mr_state(s)":1,"current_rewards":[[39.0,40.0,38.0,16.0,43.0,28.0,13.0,1.0],[43.0,31.0,28.0,26.0,28.0,16.0,23.0,11.0]],"ev.mst":459.199683878375,"ev.rt":431.517182504754,"flagUpdatedRewards":0,"observation_code":6,"observation_description":"sMEC_x_AND_sMR_s_AND_sMP_f","observation_probability":0.51792,"selected_action":"MST","step_reward":39.0,"updated_belief_mec_true_(s')":0.895895281785135,"updated_belief_mp_true_(s')":0.902647910621302,"updated_belief_mr_true_(s')":0.929519100483226},
"59":{"acu_rewards_discounted":735.380447349028,"acu_rewards_undiscounted":2321.0,"arrived_mec_state_(s')":1,"arrived_mp_state_(s')":1,"arrived_mr_state_(s')":1,"current_belief_mec_true_(s)":0.895895281785135,"current_belief_mp_true_(s)":0.902647910621302,"current_belief_mr_true_(s)":0.929519100483226,"current_mec_state(s)":1,"current_mp_state(s)":1,"current_mr_state(s)":1,"current_rewards":[[39.0,40.0,38.0,16.0,43.0,28.0,13.0,1.0],[43.0,31.0,28.0,26.0,28.0,16.0,23.0,11.0]],"ev.mst":457.865339271395,"ev.rt":439.188482219133,"flagUpdatedRewards":0,"observation_code":5,"observation_description":"sMEC_x_AND_sMR_r_s_AND_sMP_g","observation_probability":0.00512000000000001,"selected_action":"MST","step_reward":39.0,"updated_belief_mec_true_(s')":0.903076171875,"updated_belief_mp_true_(s')":0.75830078125,"updated_belief_mr_true_(s')":0.834228515625},
"60":{"acu_rewards_discounted":737.17716950952,"acu_rewards_undiscounted":2360.0,"arrived_mec_state_(s')":1,"arrived_mp_state_(s')":1,"arrived_mr_state_(s')":1,"current_belief_mec_true_(s)":0.903076171875,"current_belief_mp_true_(s)":0.75830078125,"current_belief_mr_true_(s)":0.834228515625,"current_mec_state(s)":1,"current_mp_state(s)":0,"current_mr_state(s)":1,"current_rewards":[[39.0,40.0,38.0,16.0,43.0,28.0,13.0,1.0],[43.0,31.0,28.0,26.0,28.0,16.0,23.0,11.0]],"ev.mst":467.249783208593,"ev.rt":447.738475664735,"flagUpdatedRewards":0,"observation_code":15,"observation_description":"sMEC_x_y_AND_sMR_s_AND_sMP_f","observation_probability":0.09711,"selected_action":"MST","step_reward":39.0,"updated_belief_mec_true_(s')":0.876288803470665,"updated_belief_mp_true_(s')":0.91169784001415,"updated_belief_mr_true_(s')":0.936047028580477},
"61":{"acu_rewards_discounted":738.884055561986,"acu_rewards_undiscounted":2399.0,"arrived_mec_state_(s')":1,"arrived_mp_state_(s')":1,"arrived_mr_state_(s')":1,"current_belief_mec_true_(s)":0.876288803470665,"current_belief_mp_true_(s)":0.91169784001415,"current_belief_mr_true_(s)":0.936047028580477,"current_mec_state(s)":1,"current_mp_state(s)":1,"current_mr_state(s)":1,"current_rewards":[[39.0,40.0,38.0,16.0,43.0,28.0,13.0,1.0],[43.0,31.0,28.0,26.0,28.0,16.0,23.0,11.0]],"ev.mst":457.491017540905,"ev.rt":435.3355427366,"flagUpdatedRewards":0,"observation_code":6,"observation_description":"sMEC_x_AND_sMR_s_AND_sMP_f","observation_probability":0.51792,"selected_action":"MST","step_reward":39.0,"updated_belief_mec_true_(s')":0.900068451097272,"updated_belief_mp_true_(s')":0.913168540544582,"updated_belief_mr_true_(s')":0.932931300627657},
"62":{"acu_rewards_discounted":740.547175305415,"acu_rewards_undiscounted":2439.0,"arrived_mec_state_(s')":1,"arrived_mp_state_(s')":0,"arrived_mr_state_(s')":1,"current_belief_mec_true_(s)":0.900068451097272,"current_belief_mp_true_(s)":0.913168540544582,"current_belief_mr_true_(s)":0.932931300627657,"current_mec_state(s)":1,"current_mp_state(s)":1,"current_mr_state(s)":1,"current_rewards":[[39.0,40.0,38.0,16.0,43.0,28.0,13.0,1.0],[43.0,31.0,28.0,26.0,28.0,16.0,23.0,11.0]],"ev.mst":466.400807729522,"ev.rt":438.426854734578,"flagUpdatedRewards":0,"observation_code":4,"observation_description":"sMEC_x_AND_sMR_r_s_AND_sMP_f_g","observation_probability":0.02944,"selected_action":"MST","step_reward":40.0,"updated_belief_mec_true_(s')":0.905031201743825,"updated_belief_mp_true_(s')":0.834939473457217,"updated_belief_mr_true_(s')":0.834021128274557},
"63":{"acu_rewards_discounted":742.127139061673,"acu_rewards_undiscounted":2479.0,"arrived_mec_state_(s')":1,"arrived_mp_state_(s')":0,"arrived_mr_state_(s')":1,"current_belief_mec_true_(s)":0.905031201743825,"current_belief_mp_true_(s)":0.834939473457217,"current_belief_mr_true_(s)":0.834021128274557,"current_mec_state(s)":1,"current_mp_state(s)":1,"current_mr_state(s)":1,"current_rewards":[[39.0,40.0,38.0,16.0,43.0,28.0,13.0,1.0],[43.0,31.0,28.0,26.0,28.0,16.0,23.0,11.0]],"ev.mst":475.566194737985,"ev.rt":438.937841365219,"flagUpdatedRewards":0,"observation_code":7,"observation_description":"sMEC_x_AND_sMR_s_AND_sMP_f_g","observation_probability":0.14352,"selected_action":"MST","step_reward":40.0,"updated_belief_mec_true_(s')":0.901884029053324,"updated_belief_mp_true_(s')":0.803231266095072,"updated_belief_mr_true_(s')":0.936934111693807},
"64":{"acu_rewards_discounted":743.590580490906,"acu_rewards_undiscounted":2518.0,"arrived_mec_state_(s')":1,"arrived_mp_state_(s')":1,"arrived_mr_state_(s')":1,"current_belief_mec_true_(s)":0.901884029053324,"current_belief_mp_true_(s)":0.803231266095072,"current_belief_mr_true_(s)":0.936934111693807,"current_mec_state(s)":1,"current_mp_state(s)":1,"current_mr_state(s)":0,"current_rewards":[[39.0,40.0,38.0,16.0,43.0,28.0,13.0,1.0],[43.0,31.0,28.0,26.0,28.0,16.0,23.0,11.0]],"ev.mst":456.694871071959,"ev.rt":425.630353424366,"flagUpdatedRewards":0,"observation_code":15,"observation_description":"sMEC_x_y_AND_sMR_s_AND_sMP_f","observation_probability":0.09711,"selected_action":"MST","step_reward":39.0,"updated_belief_mec_true_(s')":0.869426984317883,"updated_belief_mp_true_(s')":0.904970155140515,"updated_belief_mr_true_(s')":0.935274787517788},
"65":{"acu_rewards_discounted":744.980849848678,"acu_rewards_undiscounted":2557.0,"arrived_mec_state_(s')":1,"arrived_mp_state_(s')":1,"arrived_mr_state_(s')":1,"current_belief_mec_true_(s)":0.869426984317883,"current_belief_mp_true_(s)":0.904970155140515,"current_belief_mr_true_(s)":0.935274787517788,"current_mec_state(s)":1,"current_mp_state(s)":1,"current_mr_state(s)":1,"current_rewards":[[39.0,40.0,38.0,16.0,43.0,28.0,13.0,1.0],[43.0,31.0,28.0,26.0,28.0,16.0,23.0,11.0]],"ev.mst":475.441010626023,"ev.rt":450.848216966399,"flagUpdatedRewards":0,"observation_code":24,"observation_description":"sMEC_y_AND_sMR_s_AND_sMP_f","observation_probability":0.03237,"selected_action":"MST","step_reward":39.0,"updated_belief_mec_true_(s')":0.810213174744464,"updated_belief_mp_true_(s')":0.907778113910975,"updated_belief_mr_true_(s')":0.942316691232208},
"66":{"acu_rewards_discounted":746.301605738561,"acu_rewards_undiscounted":2596.0,"arrived_mec_state_(s')":1,"arrived_mp_state_(s')":1,"arrived_mr_state_(s')":1,"current_belief_mec_true_(s)":0.810213174744464,"current_belief_mp_true_(s)":0.907778113910975,"current_belief_mr_true_(s)":0.942316691232208,"current_mec_state(s)":1,"current_mp_state(s)":1,"current_mr_state(s)":1,"current_rewards":[[39.0,40.0,38.0,16.0,43.0,28.0,13.0,1.0],[43.0,31.0,28.0,26.0,28.0,16.0,23.0,11.0]],"ev.mst":462.931138923758,"ev.rt":429.810610178059,"flagUpdatedRewards":0,"observation_code":24,"observation_description":"sMEC_y_AND_sMR_s_AND_sMP_f","observation_probability":0.03237,"selected_action":"MST","step_reward":39.0,"updated_belief_mec_true_(s')":0.811672159426537,"updated_belief_mp_true_(s')":0.909613020738067,"updated_belief_mr_true_(s')":0.931157675486346},
"67":{"acu_rewards_discounted":747.685012869375,"acu_rewards_undiscounted":2639.0,"arrived_mec_state_(s')":1,"arrived_mp_state_(s')":1,"arrived_mr_state_(s')":1,"current_belief_mec_true_(s)":0.811672159426537,"current_belief_mp_true_(s)":0.909613020738067,"current_belief_mr_true_(s)":0.931157675486346,"current_mec_state(s)":1,"current_mp_state(s)":1,"current_mr_state(s)":1,"current_rewards":[[39.0,40.0,38.0,16.0,43.0,28.0,13.0,1.0],[43.0,31.0,28.0,26.0,28.0,16.0,23.0,11.0]],"ev.mst":454.563037236847,"ev.rt":457.549529351006,"flagUpdatedRewards":0,"observation_code":0,"observation_description":"sMEC_x_AND_sMR_r_AND_sMP_f","observation_probability":0.0312,"selected_action":"RT","step_reward":43.0,"updated_belief_mec_true_(s')":0.880305864757113,"updated_belief_mp_true_(s')":0.849749348632075,"updated_belief_mr_true_(s')":0.91122551251327},
"68":{"acu_rewards_discounted":748.907558705908,"acu_rewards_undiscounted":2679.0,"arrived_mec_state_(s')":1,"arrived_mp_state_(s')":0,"arrived_mr_state_(s')":1,"current_belief_mec_true_(s)":0.880305864757113,"current_belief_mp_true_(s)":0.849749348632075,"current_belief_mr_true_(s)":0.91122551251327,"current_mec_state(s)":1,"current_mp_state(s)":1,"current_mr_state(s)":1,"current_rewards":[[39.0,40.0,38.0,16.0,43.0,28.0,13.0,1.0],[43.0,31.0,28.0,26.0,28.0,16.0,23.0,11.0]],"ev.mst":465.1085867261,"ev.rt":439.241870580374,"flagUpdatedRewards":0,"observation_code":6,"observation_description":"sMEC_x_AND_sMR_s_AND_sMP_f","observation_probability":0.41808,"selected_action":"MST","step_reward":40.0,"updated_belief_mec_true_(s')":0.893866889147158,"updated_belief_mp_true_(s')":0.911755747159107,"updated_belief_mr_true_(s')":0.93793584738234},
"69":{"acu_rewards_discounted":750.039941786996,"acu_rewards_undiscounted":2718.0,"arrived_mec_state_(s')":1,"arrived_mp_state_(s')":1,"arrived_mr_state_(s')":1,"current_belief_mec_true_(s)":0.893866889147158,"current_belief_mp_true_(s)":0.911755747159107,"current_belief_mr_true_(s)":0.93793584738234,"current_mec_state(s)":1,"current_mp_state(s)":1,"current_mr_state(s)":1,"current_rewards":[[39.0,40.0,38.0,16.0,43.0,28.0,13.0,1.0],[43.0,31.0,28.0,26.0,28.0,16.0,23.0,11.0]],"ev.mst":453.198402095764,"ev.rt":450.629617186434,"flagUpdatedRewards":0,"observation_code":7,"observation_description":"sMEC_x_AND_sMR_s_AND_sMP_f_g","observation_probability":0.08112,"selected_action":"MST","step_reward":39.0,"updated_belief_mec_true_(s')":0.896259750620406,"updated_belief_mp_true_(s')":0.836687651982,"updated_belief_mr_true_(s')":0.937988119805575}}